LICENSE
MANIFEST.in
README.md
package.json
setup.py
dash_mention_input/DashMentionInput.py
dash_mention_input/__init__.py
dash_mention_input/_imports_.py
dash_mention_input/dash_mention_input.min.js
dash_mention_input/dash_mention_input.min.js.map
dash_mention_input/metadata.json
dash_mention_input/package-info.json
dash_mention_input.egg-info/PKG-INFO
dash_mention_input.egg-info/SOURCES.txt
dash_mention_input.egg-info/dependency_links.txt
dash_mention_input.egg-info/top_level.txt