Metadata-Version: 1.1
Name: dash-mention-input
Version: 0.0.4
Summary: Input with @mention support
Home-page: UNKNOWN
Author: Dmytro Cherkaskyy <dmytro@pelico.io>
Author-email: UNKNOWN
License: MIT
Platform: UNKNOWN
Classifier: Framework :: Dash
